autogamess/__init__.py
autogamess/bat_maker.py
autogamess/config.py
autogamess/convert_ir_units.py
autogamess/data_finder.py
autogamess/dictionaries.py
autogamess/double_check_sheet.py
autogamess/fill_spreadsheets.py
autogamess/generate_scaling_factors.py
autogamess/get_data.py
autogamess/hes2raman.py
autogamess/input_builder.py
autogamess/make_plot.py
autogamess/new_project.py
autogamess/opt2hes.py
autogamess/prep_restart.py
autogamess/sort_inps.py
autogamess/sort_logs.py
autogamess/classes/INPUT.py
autogamess/classes/PROJECT.py
autogamess/classes/__init__.py
autogamess/plots/__init__.py
autogamess/plots/make_kde.py
autogamess/plots/make_scatter.py
autogamess/plots/prep_data.py
autogamess/stats/__init__.py
autogamess-1.1.57.dist-info/LICENSE
autogamess-1.1.57.dist-info/METADATA
autogamess-1.1.57.dist-info/WHEEL
autogamess-1.1.57.dist-info/top_level.txt
autogamess-1.1.57.dist-info/RECORD
